converter.py
numbersystems-1.50.dist-info/LICENSE
numbersystems-1.50.dist-info/METADATA
numbersystems-1.50.dist-info/WHEEL
numbersystems-1.50.dist-info/top_level.txt
numbersystems-1.50.dist-info/RECORD
