Metadata-Version: 2.1
Name: numbersystems
Version: 1.50
Summary: Python Module to convert one Number System to other with ease
Home-page: https://github.com/aryanshdev/numbersystems
Author: Aryansh Gupta
Author-email: Aryanshappmaker@gmail.com
License: UNKNOWN
Platform: UNKNOWN
Requires-Python: >=3.1
